{
  "main": {
    "id": "f3579a0eb71de609",
    "type": "split",
    "children": [
      {
        "id": "6391de2efa081f4f",
        "type": "tabs",
        "children": [
          {
            "id": "9c8b017611517981",
            "type": "leaf",
            "state": {
              "type": "empty",
              "state": {},
              "icon": "lucide-file",
              "title": "Nouvel onglet"
            }
          }
        ]
      }
    ],
    "direction": "vertical"
  },
  "left": {
    "id": "889edd80d562f549",
    "type": "split",
    "children": [
      {
        "id": "3dbdd48c152a2187",
        "type": "tabs",
        "children": [
          {
            "id": "3a70b6475261b909",
            "type": "leaf",
            "state": {
              "type": "file-explorer",
              "state": {
                "sortOrder": "alphabetical",
                "autoReveal": false
              },
              "icon": "lucide-folder-closed",
              "title": "Explorateur de fichiers"
            }
          },
          {
            "id": "9d6207ea5a09006d",
            "type": "leaf",
            "state": {
              "type": "search",
              "state": {
                "query": "",
                "matchingCase": false,
                "explainSearch": false,
                "collapseAll": false,
                "extraContext": false,
                "sortOrder": "alphabetical"
              },
              "icon": "lucide-search",
              "title": "Rechercher"
            }
          },
          {
            "id": "95ffc8bae75080a8",
            "type": "leaf",
            "state": {
              "type": "bookmarks",
              "state": {},
              "icon": "lucide-bookmark",
              "title": "Signet"
            }
          }
        ]
      }
    ],
    "direction": "horizontal",
    "width": 300
  },
  "right": {
    "id": "a960de31e0fcd32b",
    "type": "split",
    "children": [
      {
        "id": "ceb608601d17cd35",
        "type": "tabs",
        "children": [
          {
            "id": "774e5cd4a4d4f98d",
            "type": "leaf",
            "state": {
              "type": "backlink",
              "state": {
                "collapseAll": false,
                "extraContext": false,
                "sortOrder": "alphabetical",
                "showSearch": false,
                "searchQuery": "",
                "backlinkCollapsed": false,
                "unlinkedCollapsed": true
              },
              "icon": "links-coming-in",
              "title": "Rétroliens"
            }
          },
          {
            "id": "278ccb202cac3256",
            "type": "leaf",
            "state": {
              "type": "outgoing-link",
              "state": {
                "linksCollapsed": false,
                "unlinkedCollapsed": true
              },
              "icon": "links-going-out",
              "title": "Liens sortants"
            }
          },
          {
            "id": "502c31db333dd35d",
            "type": "leaf",
            "state": {
              "type": "tag",
              "state": {
                "sortOrder": "frequency",
                "useHierarchy": true,
                "showSearch": false,
                "searchQuery": ""
              },
              "icon": "lucide-tags",
              "title": "Mots-clés"
            }
          },
          {
            "id": "eef0bd43f5b41d59",
            "type": "leaf",
            "state": {
              "type": "outline",
              "state": {
                "followCursor": false,
                "showSearch": false,
                "searchQuery": ""
              },
              "icon": "lucide-list",
              "title": "Plan"
            }
          }
        ]
      }
    ],
    "direction": "horizontal",
    "width": 300,
    "collapsed": true
  },
  "left-ribbon": {
    "hiddenItems": {
      "bases:Create new base": false,
      "switcher:Ouvrir le sélecteur rapide": false,
      "graph:Ouvrir la vue graphique": false,
      "canvas:Créer une nouvelle toile": false,
      "daily-notes:Ouvrir la note quotidienne": false,
      "templates:Insérer le modèle": false,
      "command-palette:Ouvrir la palette de commandes": false
    }
  },
  "active": "9c8b017611517981",
  "lastOpenFiles": []
}